gzeuge/__init__.py
gzeuge/graphs/hypergraph.py
gzeuge/graphs/pygraph.py
gzeuge/graphs/schema.py
gzeuge/main.py
gzeuge-0.1.0.dist-info/METADATA
gzeuge-0.1.0.dist-info/WHEEL
gzeuge-0.1.0.dist-info/RECORD
