Metadata-Version: 2.1
Name: gzeuge
Version: 0.1.0
Summary: A collection of basic and common graph utilities
Author: Kun Lu
Author-email: kun.lu.brain@gmail.com
Requires-Python: >=3.9,<4.0
Classifier: Programming Language :: Python :: 3
Classifier: Programming Language :: Python :: 3.9
Classifier: Programming Language :: Python :: 3.10
Classifier: Programming Language :: Python :: 3.11
Classifier: Programming Language :: Python :: 3.12
Requires-Dist: fire (>=0.5.0,<0.6.0)
Requires-Dist: graphviz (>=0.20.1,<0.21.0)
Requires-Dist: jinja2 (>=3.1.2,<4.0.0)
Requires-Dist: jsonlines (>=4.0.0,<5.0.0)
Requires-Dist: jsonpickle (>=3.0.2,<4.0.0)
Requires-Dist: networkx (>=3.1,<4.0)
Requires-Dist: pydantic (>=2.3.0,<3.0.0)
Requires-Dist: pyparsing (>=3.1.1,<4.0.0)
Requires-Dist: pyyaml (>=6.0.1,<7.0.0)
